<?xml version="1.0" encoding="UTF-8" standalone="yes"?>
<CollaborationAgreement enabled="true">
    <Partner id="exp">
        <PartyIds>
            <PartyId type="AS2-Name">exp</PartyId>
            <PartyId type="AS3-Name">exp</PartyId>
            <PartyId type="URI">http://localhost:8081/pontonxp/SoapListener</PartyId>
        </PartyIds>
    </Partner>
    <Partner id="deham">
        <PartyIds>
            <PartyId type="AS2-Name">deham</PartyId>
            <PartyId type="AS3-Name">deham</PartyId>
            <PartyId type="URI">http://localhost:8081/pontonxp/SoapListener</PartyId>
        </PartyIds>
    </Partner>
    <PayloadDocuments>
        <Document type="BINARY" version="1" schemaLocation="BINARY" schemaSet="BINARY"/>
    </PayloadDocuments>
    <Communications>
        <Communication SenderRefId="exp" ReceiverRefId="deham">
            <Pipeline id="Messenger 2.1">
                <Option name="Compression" value="Zlib" type="list"/>
                <Option name="validation" value="true" type="boolean"/>
            </Pipeline>
            <Packaging id="EbXml20">
                <Option name="RequestAck" value="unsigned" type="list"/>
                <Option name="DuplicateElimination" value="true" type="boolean"/>
                <Option name="SyncReply" value="true" type="boolean"/>
            </Packaging>
            <Transport id="HTTP">
                <URL>http://localhost:8081/pontonxp/SoapListener</URL>
                <FallbackURL></FallbackURL>
                <NumberOfRetries>2</NumberOfRetries>
                <RetryInterval>60</RetryInterval>
            </Transport>
        </Communication>
        <Communication SenderRefId="deham" ReceiverRefId="exp">
            <Pipeline id="Messenger 2.1">
                <Option name="Compression" value="Zlib" type="list"/>
                <Option name="validation" value="true" type="boolean"/>
            </Pipeline>
            <Packaging id="EbXml20">
                <Option name="RequestAck" value="unsigned" type="list"/>
            </Packaging>
            <Transport id="HTTP">
                <URL>http://localhost:8081/pontonxp/SoapListener</URL>
                <FallbackURL></FallbackURL>
                <NumberOfRetries>2</NumberOfRetries>
                <RetryInterval>60</RetryInterval>
                <NumberOfParallelDeliveries>5</NumberOfParallelDeliveries>
            </Transport>
        </Communication>
    </Communications>
    <CompatibilityVersion>3.3</CompatibilityVersion>
</CollaborationAgreement>
